Metadata-Version: 1.1
Name: fs.onedatafs
Version: 18.2.2.0
Summary: Onedata filesystem for PyFilesystem2
Home-page: https://github.com/onedata/fs-onedatafs
Author: Bartek Kryza
Author-email: bkryza@gmail.com
License: MIT
Keywords: pyfilesystem,Onedata,oneclient
Platform: linux
Classifier: Development Status :: 4 - Beta
Classifier: Intended Audience :: Developers
Classifier: License :: OSI Approved :: MIT License
Classifier: Operating System :: OS Independent
Classifier: Programming Language :: Python
Classifier: Programming Language :: Python :: 2.7
Classifier: Programming Language :: Python :: 3.3
Classifier: Programming Language :: Python :: 3.4
Classifier: Programming Language :: Python :: 3.5
Classifier: Programming Language :: Python :: 3.6
Classifier: Programming Language :: Python :: 3.7
Classifier: Topic :: System :: Filesystems
